an_abracadabra/__init__.py
an_abracadabra/abracadabra.py
an_abracadabra-1.5.1.dist-info/LICENSE
an_abracadabra-1.5.1.dist-info/METADATA
an_abracadabra-1.5.1.dist-info/WHEEL
an_abracadabra-1.5.1.dist-info/top_level.txt
an_abracadabra-1.5.1.dist-info/RECORD
