Metadata-Version: 2.1
Name: an_abracadabra
Version: 1.5.1
Summary: A package for an_abracadabra.
Home-page: https://github.com/Atsushi888/Atsushi888
Author: Atsushi888
Author-email: Atsushi888 <vtgrotxu@gmail.com>
Project-URL: Homepage, https://github.com/Atsushi888/an_abracadabra
Project-URL: Repository, https://github.com/Atsushi888/an_abracadabra
Requires-Python: >=3.6
License-File: LICENSE
